byted_overpass_data_edc_dreamcloth_task_rpc/__init__.py
byted_overpass_data_edc_dreamcloth_task_rpc-0.0.1.dist-info/METADATA
byted_overpass_data_edc_dreamcloth_task_rpc-0.0.1.dist-info/WHEEL
byted_overpass_data_edc_dreamcloth_task_rpc-0.0.1.dist-info/top_level.txt
byted_overpass_data_edc_dreamcloth_task_rpc-0.0.1.dist-info/RECORD
